way/__init__.py
way/fs/__init__.py
way-0.0.1.dist-info/WHEEL
way-0.0.1.dist-info/METADATA
way-0.0.1.dist-info/RECORD
